fast/__init__.py
fast/_version.py
fast/ao_power_spectra.py
fast/comms.py
fast/complete_orbit_simulation.py
fast/conf.py
fast/fast.py
fast/funcs.py
fast/turbulence_models.py
fast_aosim-0.1.7.dist-info/licenses/LICENSE.md
fast_aosim-0.1.7.dist-info/METADATA
fast_aosim-0.1.7.dist-info/WHEEL
fast_aosim-0.1.7.dist-info/top_level.txt
fast_aosim-0.1.7.dist-info/RECORD
