Metadata-Version: 2.4
Name: fast-aosim
Version: 0.1.7
Summary: Fourier domain Adaptive optics Simulation Tool
Author-email: Ollie Farley <o.j.d.farley@durham.ac.uk>
License:                     GNU GENERAL PUBLIC LICENSE
Project-URL: Homepage, https://github.com/ojdf/fast
Project-URL: Documentation, https://ojdf.github.io/fast
Classifier: Programming Language :: Python :: 3
Requires-Python: >=3.7
License-File: LICENSE.md
Requires-Dist: numpy
Requires-Dist: scipy
Requires-Dist: aotools>=1.0.7
Requires-Dist: astropy
Requires-Dist: tqdm
Requires-Dist: skyfield
Provides-Extra: test
Requires-Dist: pytest; extra == "test"
Requires-Dist: coverage; extra == "test"
Dynamic: license-file
